[{"id": "16816927859223537240", "genre": "現代ファンタジー", "label": ["魔法少女", "マジカルドリーマー", "夢喰い", "プリキュア", "主題歌あり", "マッスルファンタジー", "カクヨムオンリー"], "stars": "44"}, {"id": "16816927860163250279", "genre": "現代ドラマ", "label": ["現代", "青春", "友情", "恋愛", "小説", "仕事", "人生", "大河"], "stars": "27"}, {"id": "16816927860163633387", "genre": "ラブコメ", "label": ["百合", "ガールズラブ", "社会人百合"], "stars": "15"}, {"id": "16816927860165300934", "genre": "異世界ファンタジー", "label": ["ハッピーエンド", "不遇", "人魚", "ファンタジー"], "stars": "28"}, {"id": "16816927860165696400", "genre": "ラブコメ", "label": ["ファンタジー", "男主人公", "魔王", "ラブコメ"], "stars": "75"}, {"id": "16816927860166669296", "genre": "ホラー", "label": ["鬼", "美少女", "青春", "背信", "昔話", "安倍晴明", "戻橋", "犠牲"], "stars": "10"}, {"id": "16816927860172805100", "genre": "SF", "label": ["宮大工", "宇宙人", "宇宙飛行士", "ＵＦＯ"], "stars": "20"}]